nanosphere/__init__.py
nanosphere/cli.py
nanosphere/util.py
nanosphere/service/__init__.py
nanosphere/service/auth.py
nanosphere/service/push.py
nanosphere/service/sms.py
nanosphere-0.1.0.dist-info/DESCRIPTION.rst
nanosphere-0.1.0.dist-info/METADATA
nanosphere-0.1.0.dist-info/RECORD
nanosphere-0.1.0.dist-info/WHEEL
nanosphere-0.1.0.dist-info/entry_points.txt
nanosphere-0.1.0.dist-info/metadata.json
nanosphere-0.1.0.dist-info/top_level.txt
