Metadata-Version: 2.0
Name: nanosphere
Version: 0.1.0
Summary: A collection of nanservices
Home-page: https://github.com/walkr/nanosphere
Author: Tony Walker
Author-email: walkr.walkr@gmail.com
License: MIT
Keywords: nanosphere
Platform: UNKNOWN
Classifier: Development Status :: 2 - Pre-Alpha
Classifier: Intended Audience :: Developers
Classifier: License :: OSI Approved :: MIT License
Classifier: Natural Language :: English
Classifier: Programming Language :: Python :: 2
Classifier: Programming Language :: Python :: 2.7
Classifier: Programming Language :: Python :: 3
Classifier: Programming Language :: Python :: 3.3
Classifier: Programming Language :: Python :: 3.4
Classifier: Programming Language :: Python :: 3.5
Requires-Dist: apns
Requires-Dist: click
Requires-Dist: nanoservice
Requires-Dist: pyjwt
Requires-Dist: twilio
